odoo/addons/mrp_component_operation_scrap_reason/README.rst
odoo/addons/mrp_component_operation_scrap_reason/__init__.py
odoo/addons/mrp_component_operation_scrap_reason/__manifest__.py
odoo/addons/mrp_component_operation_scrap_reason/i18n/es.po
odoo/addons/mrp_component_operation_scrap_reason/i18n/it.po
odoo/addons/mrp_component_operation_scrap_reason/i18n/mrp_component_operation_scrap_reason.pot
odoo/addons/mrp_component_operation_scrap_reason/i18n/tr.po
odoo/addons/mrp_component_operation_scrap_reason/readme/CONTRIBUTORS.md
odoo/addons/mrp_component_operation_scrap_reason/readme/DESCRIPTION.md
odoo/addons/mrp_component_operation_scrap_reason/static/description/icon.png
odoo/addons/mrp_component_operation_scrap_reason/static/description/index.html
odoo/addons/mrp_component_operation_scrap_reason/wizards/__init__.py
odoo/addons/mrp_component_operation_scrap_reason/wizards/mrp_component_operate.py
odoo/addons/mrp_component_operation_scrap_reason/wizards/mrp_component_operate_wizard.xml
odoo_addon_mrp_component_operation_scrap_reason-17.0.1.0.1.dist-info/METADATA
odoo_addon_mrp_component_operation_scrap_reason-17.0.1.0.1.dist-info/WHEEL
odoo_addon_mrp_component_operation_scrap_reason-17.0.1.0.1.dist-info/top_level.txt
odoo_addon_mrp_component_operation_scrap_reason-17.0.1.0.1.dist-info/RECORD
