Metadata-Version: 2.1
Name: odoo-addon-mrp_component_operation_scrap_reason
Version: 17.0.1.0.1
Requires-Python: >=3.10
Requires-Dist: odoo-addon-mrp_component_operation>=17.0dev,<17.1dev
Requires-Dist: odoo-addon-scrap_reason_code>=17.0dev,<17.1dev
Requires-Dist: odoo>=17.0a,<17.1dev
Summary: Allows to pass a reason to scrap with MRP component operation
Home-page: https://github.com/OCA/manufacture
License: AGPL-3
Author: ForgeFlow, Odoo Community Association (OCA)
Author-email: support@odoo-community.org
Classifier: Programming Language :: Python
Classifier: Framework :: Odoo
Classifier: Framework :: Odoo :: 17.0
Classifier: License :: OSI Approved :: GNU Affero General Public License v3
